flask_pydantic/__init__.py
flask_pydantic/converters.py
flask_pydantic/core.py
flask_pydantic/exceptions.py
flask_pydantic/version.py
flask_pydantic-0.13.2.dist-info/licenses/LICENSE.txt
flask_pydantic-0.13.2.dist-info/WHEEL
flask_pydantic-0.13.2.dist-info/METADATA
flask_pydantic-0.13.2.dist-info/RECORD
