Metadata-Version: 2.4
Name: Flask-Pydantic
Version: 0.13.2
Summary: Flask extension for integration with Pydantic library.
Author: Jiri Bauer
Maintainer-email: Pallets <contact@palletsprojects.com>
Requires-Python: >=3.7
Classifier: Environment :: Web Environment
Classifier: Framework :: Flask
Classifier: Intended Audience :: Developers
Classifier: License :: OSI Approved :: MIT License
Classifier: Operating System :: OS Independent
Classifier: Programming Language :: Python
Classifier: Topic :: Internet :: WWW/HTTP :: Dynamic Content
Classifier: Topic :: Software Development :: Libraries :: Python Modules
License-File: LICENSE.txt
Requires-Dist: Flask
Requires-Dist: pydantic>=2.0
Requires-Dist: typing_extensions>=4.1.1; python_version < '3.8'
Project-URL: Chat, https://discord.gg/pallets
Project-URL: Donate, https://palletsprojects.com/donate
Project-URL: Source, https://github.com/pallets-eco/flask-pydantic
